cavey_gw2_tools/__init__.py
cavey_gw2_tools/__main__.py
cavey_gw2_tools/main.py
cavey_gw2_tools-0.1.0.dist-info/entry_points.txt
cavey_gw2_tools-0.1.0.dist-info/METADATA
cavey_gw2_tools-0.1.0.dist-info/WHEEL
cavey_gw2_tools-0.1.0.dist-info/RECORD
