Metadata-Version: 2.1
Name: cavey-gw2-tools
Version: 0.1.0
Summary: 
Author: Cavey
Author-email: m.123051427@gmail.com
Requires-Python: >=3.11,<4.0
Classifier: Programming Language :: Python :: 3
Classifier: Programming Language :: Python :: 3.11
Requires-Dist: pymem (>=1.10.0,<2.0.0)
Requires-Dist: typer[all] (>=0.7.0,<0.8.0)
